botwriter/__init__.py
botwriter-0.1.4.dist-info/entry_points.txt
botwriter-0.1.4.dist-info/WHEEL
botwriter-0.1.4.dist-info/METADATA
botwriter-0.1.4.dist-info/RECORD
