Metadata-Version: 2.1
Name: botwriter
Version: 0.1.4
Summary: Botwriter provides a simple and comprehensive toolset for saving auth credentials and settings to Infeed as well as fetching data streams for your Botwriter plugins
Author: Mattis Abrahamsson
Author-email: mattis.abrahamsson@gmail.com
Requires-Python: >=3.8,<4.0
Classifier: Programming Language :: Python :: 3
Classifier: Programming Language :: Python :: 3.8
Requires-Dist: pandas (>=1.0.1,<2.0.0)
Requires-Dist: requests (>=2.22.0,<3.0.0)
